neural_structured_learning/__init__.py
neural_structured_learning/version.py
neural_structured_learning/configs/__init__.py
neural_structured_learning/configs/configs.py
neural_structured_learning/estimator/__init__.py
neural_structured_learning/estimator/adversarial_regularization.py
neural_structured_learning/estimator/adversarial_regularization_test.py
neural_structured_learning/estimator/graph_regularization.py
neural_structured_learning/estimator/graph_regularization_test.py
neural_structured_learning/experimental/__init__.py
neural_structured_learning/experimental/gnn.py
neural_structured_learning/keras/__init__.py
neural_structured_learning/keras/adversarial_regularization.py
neural_structured_learning/keras/adversarial_regularization_multi_device_test.py
neural_structured_learning/keras/adversarial_regularization_test.py
neural_structured_learning/keras/graph_regularization.py
neural_structured_learning/keras/graph_regularization_test.py
neural_structured_learning/keras/layers/__init__.py
neural_structured_learning/keras/layers/layers_test.py
neural_structured_learning/keras/layers/neighbor_features.py
neural_structured_learning/keras/layers/neighbor_features_test.py
neural_structured_learning/keras/layers/pairwise_distance.py
neural_structured_learning/keras/layers/pairwise_distance_test.py
neural_structured_learning/lib/__init__.py
neural_structured_learning/lib/abstract_gen_neighbor.py
neural_structured_learning/lib/adversarial_neighbor.py
neural_structured_learning/lib/adversarial_neighbor_test.py
neural_structured_learning/lib/distances.py
neural_structured_learning/lib/distances_test.py
neural_structured_learning/lib/regularizer.py
neural_structured_learning/lib/regularizer_test.py
neural_structured_learning/lib/utils.py
neural_structured_learning/lib/utils_test.py
neural_structured_learning/tools/__init__.py
neural_structured_learning/tools/build_docs.py
neural_structured_learning/tools/build_graph.py
neural_structured_learning-1.4.0.dist-info/LICENSE
neural_structured_learning-1.4.0.dist-info/METADATA
neural_structured_learning-1.4.0.dist-info/WHEEL
neural_structured_learning-1.4.0.dist-info/top_level.txt
neural_structured_learning-1.4.0.dist-info/RECORD
