Metadata-Version: 2.1
Name: neural-structured-learning
Version: 1.4.0
Summary: Neural Structured Learning is an open-source TensorFlow framework to train neural networks with structured signals
Home-page: https://github.com/tensorflow/neural-structured-learning
Author: Google LLC
License: UNKNOWN
Platform: UNKNOWN
Classifier: Programming Language :: Python :: 2
Classifier: Programming Language :: Python :: 3
Classifier: License :: OSI Approved :: Apache Software License
Classifier: Operating System :: OS Independent
License-File: LICENSE
Requires-Dist: absl-py
Requires-Dist: attrs
Requires-Dist: scipy
Requires-Dist: six
